django_excel_storage/__init__.py
django_excel_storage/excel_storage.py
django_excel_storage-2.0.11.dist-info/METADATA
django_excel_storage-2.0.11.dist-info/WHEEL
django_excel_storage-2.0.11.dist-info/top_level.txt
django_excel_storage-2.0.11.dist-info/RECORD
