Metadata-Version: 2.1
Name: django-excel-storage
Version: 2.0.11
Summary: Django Excel Storage
Home-page: https://github.com/django-xxx/django-excel-storage
Author: Hackathon
Author-email: kimi.huang@brightcells.com
Keywords: django-excel-storage
Classifier: Development Status :: 5 - Production/Stable
Classifier: Environment :: Web Environment
Classifier: Framework :: Django
Classifier: Intended Audience :: Developers
Classifier: Programming Language :: Python
Classifier: Topic :: Software Development :: Libraries :: Python Modules
Classifier: Topic :: Office/Business :: Financial :: Spreadsheet
Requires-Dist: django-six (>=1.0.4)
Requires-Dist: excel-base (>=1.0.3)
